mdplist/__init__.py
mdplist/mdplist_cli.py
mdplist/parser.py
mdplistlib-0.1.2.dist-info/LICENSE
mdplistlib-0.1.2.dist-info/METADATA
mdplistlib-0.1.2.dist-info/WHEEL
mdplistlib-0.1.2.dist-info/entry_points.txt
mdplistlib-0.1.2.dist-info/top_level.txt
mdplistlib-0.1.2.dist-info/RECORD
