Metadata-Version: 2.1
Name: mdplistlib
Version: 0.1.2
Summary: A library for parsing DEBA/MDPLIST files.
Home-page: https://github.com/snoop168/mdplistlib
Author: John Hyla
Author-email: jfhyla@gmail.com
License: MIT
Classifier: Programming Language :: Python :: 3
Classifier: Programming Language :: Python :: 3.6
Classifier: Programming Language :: Python :: 3.7
Classifier: Programming Language :: Python :: 3.8
Classifier: Programming Language :: Python :: 3.9
Classifier: License :: OSI Approved :: MIT License
Classifier: Operating System :: OS Independent
Requires-Python: >=3.6
License-File: LICENSE
